napalm_aoscx/__init__.py
napalm_aoscx/aoscx.py
napalm_aoscx/utils/__init__.py
napalm_aruba_cx-0.1.4.dist-info/LICENSE
napalm_aruba_cx-0.1.4.dist-info/METADATA
napalm_aruba_cx-0.1.4.dist-info/WHEEL
napalm_aruba_cx-0.1.4.dist-info/top_level.txt
napalm_aruba_cx-0.1.4.dist-info/RECORD
