Metadata-Version: 2.1
Name: napalm-aruba-cx
Version: 0.1.4
Summary: NAPALM drivers for Aruba AOS-CX Switches
Home-page: https://github.com/napalm-automation-community/napalm-aruba-cx
Author: Aruba Automation
Author-email: aruba-automation@hpe.com
License: UNKNOWN
Platform: UNKNOWN
Classifier: Programming Language :: Python :: 3
Classifier: Programming Language :: Python :: 3.6
Classifier: Programming Language :: Python :: 3.7
Classifier: Programming Language :: Python :: 3.8
Classifier: License :: OSI Approved :: Apache Software License
Classifier: Operating System :: OS Independent
Requires-Python: >=3.6
License-File: LICENSE
